ohmypy/__init__.py
ohmypy/main.py
ohmypy/printtext.py
ohmypy/prompts.py
ohmypy/settings.py
ohmypy-0.1.0.dist-info/LICENSE
ohmypy-0.1.0.dist-info/METADATA
ohmypy-0.1.0.dist-info/WHEEL
ohmypy-0.1.0.dist-info/RECORD
