Metadata-Version: 2.1
Name: ohmypy
Version: 0.1.0
Summary: Customize Python interpreter!
License: GPLv3+
Author: lebao3105
Author-email: bao12345yocoo@gmail.com
Requires-Python: >=3.9,<4.0
Classifier: License :: Other/Proprietary License
Classifier: Programming Language :: Python :: 3
Classifier: Programming Language :: Python :: 3.9
Classifier: Programming Language :: Python :: 3.10
Classifier: Programming Language :: Python :: 3.11
Classifier: Programming Language :: Python :: 3.12
Requires-Dist: colorama (>=0.4.6,<0.5.0)
Requires-Dist: pretty-errors (>=1.2.25,<2.0.0)
Requires-Dist: requests (>=2.31.0,<3.0.0)
